{"nodes": [{"id": "meeting_20260410_freeplane", "label": "BA Tool Discovery: Freeplane (2026-04-10)", "file_type": "document", "source_file": "Granola Meeting Notes/2026-04-10 GitHub BA Tool.md", "source_location": null, "source_url": "https://github.com/freeplane/freeplane", "captured_at": "2026-04-10", "author": null, "contributor": null}, {"id": "freeplane_tool", "label": "Freeplane Mind Mapping and Knowledge Tool", "file_type": "document", "source_file": "Granola Meeting Notes/2026-04-10 GitHub BA Tool.md", "source_location": null, "source_url": "https://github.com/freeplane/freeplane", "captured_at": "2026-04-10", "author": null, "contributor": null}], "edges": [{"source": "meeting_20260410_freeplane", "target": "freeplane_tool", "relation": "references", "confidence": "EXTRACTED", "confidence_score": 1.0, "source_file": "Granola Meeting Notes/2026-04-10 GitHub BA Tool.md", "source_location": null, "weight": 1.0}], "hyperedges": []}